src/core_basics/priority_encoder.sv
module priority_encoder #(
   parameter int INPUT_LINES = 4 ,
   parameter int OUTPUT_LINES = $clog2(INPUT_LINES) 
)  (
    input logic [INPUT_LINES - 1:0] data,
    output logic [OUTPUT_LINES - 1:0] out,
    output logic valid
);

initial begin
    if (INPUT_LINES < 2) begin
        $error("INPUT_LINES must be >= 2. Got %0d", INPUT_LINES);
    end
end

logic flag;

always_comb begin
    valid = 0;
    out = '0; // default value

    flag = 1;

    for (int i = INPUT_LINES - 1; i >= 0 && flag; i--) begin
        if (data[i]) begin
            out = i[OUTPUT_LINES - 1:0];
            valid = 1;
            flag = 0;
            // break; //using flag until icarus stops complaining about this
        end
    end
end
     
endmodule

tb/core_basics/priority_encoder_tb.sv
`timescale 1ns/1ps

module priority_encoder_tb;

    // =============================================================
    //  Parameter Sweep (change INPUT_LINES here)
    // =============================================================
    parameter int INPUT_LINES  = 8;
    parameter int OUTPUT_LINES = $clog2(INPUT_LINES);

    // =============================================================
    //  DUT Signals
    // =============================================================
    logic [INPUT_LINES-1:0] data;
    logic [OUTPUT_LINES-1:0] out;
    logic valid;

    // =============================================================
    //  Instantiate DUT
    // =============================================================
    priority_encoder #(
        .INPUT_LINES(INPUT_LINES),
        .OUTPUT_LINES(OUTPUT_LINES)
    ) dut (
        .data(data),
        .out(out),
        .valid(valid)
    );

    // =============================================================
    //  Reference Model (Golden Model)
    // =============================================================
    function automatic int ref_encode(input logic [INPUT_LINES-1:0] x);
        ref_encode = -1;  // -1 means "no valid bits"
        for (int i = INPUT_LINES - 1; i >= 0; i--) begin
            if (x[i]) return i;
        end
    endfunction

    // =============================================================
    //  Compare DUT vs Reference Model
    // =============================================================
    task automatic check(input logic[INPUT_LINES-1:0] d);
        int expected_idx;
        logic expected_valid;

        data = d;
        #1;

        expected_idx   = ref_encode(d);
        expected_valid = (expected_idx != -1);

        // Output check
        if (expected_valid)
            assert(out == expected_idx[OUTPUT_LINES-1:0])
                else $error("Mismatch: data=%b expected_idx=%0d got_out=%0d",
                            d, expected_idx, out);

        // Valid check
        assert(valid == expected_valid)
            else $error("Valid mismatch: data=%b expected_valid=%0b got_valid=%0b",
                        d, expected_valid, valid);

        $display("[PASS] data=%b → out=%0d valid=%0b",
                 d, out, valid);
    endtask

    // =============================================================
    //  Main stimulus process
    // =============================================================
    initial begin
        $dumpfile("sim/waves/priority_encoder.vcd");
        $dumpvars(0, priority_encoder_tb);

        $display("\n=== Running Parameterized Priority Encoder Testbench ===");
        $display("INPUT_LINES = %0d, OUTPUT_LINES = %0d\n",
                  INPUT_LINES, OUTPUT_LINES);

        // ------------------------------------------
        // Always test the all-zero case
        // ------------------------------------------
        $display("Testing all-zero case...");
        check('0);

        // ------------------------------------------
        // Exhaustive testing for small N
        // ------------------------------------------
        if (INPUT_LINES <= 8) begin
            $display("Running exhaustive test for %0d-bit encoder...", INPUT_LINES);
            for (int i = 0; i < (1 << INPUT_LINES); i++) begin
                check(i[INPUT_LINES-1:0]);
            end
        end else begin
            // ------------------------------------------
            // Randomized testing for large N
            // ------------------------------------------
            $display("Running randomized tests for large encoder...");
            for (int j = 0; j < 200; j++) begin
                check($urandom());
            end

            // Directed tests
            check('1);                 // all ones
            check({1'b1, '0});        // MSB set
            check({1'b0, '1});        // LSB set
            check({1'b1, 1'b0, '1});  // MSB and LSB set
        end

        $display("\n=== TESTBENCH COMPLETED SUCCESSFULLY ===");
        $finish;
    end

endmodule

sim/waves/priority_encoder.vcd
$date
	Sat Nov 22 23:16:49 2025
$end
$version
	Icarus Verilog
$end
$timescale
	1ps
$end
$scope module priority_encoder_tb $end
$var wire 1 ! valid $end
$var wire 3 " out [2:0] $end
$var parameter 32 # INPUT_LINES $end
$var parameter 32 $ OUTPUT_LINES $end
$var reg 8 % data [7:0] $end
$scope function ref_encode $end
$scope begin $ivl_for_loop1 $end
$upscope $end
$upscope $end
$scope module dut $end
$var wire 8 & data [7:0] $end
$var parameter 32 ' INPUT_LINES $end
$var parameter 32 ( OUTPUT_LINES $end
$var reg 1 ) flag $end
$var reg 3 * out [2:0] $end
$var reg 1 ! valid $end
$scope begin $ivl_for_loop0 $end
$var integer 32 + i [31:0] $end
$upscope $end
$upscope $end
$scope begin $ivl_for_loop2 $end
$var integer 32 , i [31:0] $end
$upscope $end
$scope begin $ivl_for_loop3 $end
$upscope $end
$scope task check $end
$upscope $end
$upscope $end
$enddefinitions $end
$comment Show the parameter values. $end
$dumpall
b11 (
b1000 '
b11 $
b1000 #
$end
#0
$dumpvars
b0 ,
b11111111111111111111111111111111 +
b0 *
1)
b0 &
b0 %
b0 "
0!
$end
#2000
0)
1!
b11111111111111111111111111111111 +
b1 %
b1 &
b1 ,
#3000
b1 "
b1 *
b0 +
0)
1!
b10 %
b10 &
b10 ,
#4000
b0 +
0)
b1 "
b1 *
1!
b11 %
b11 &
b11 ,
#5000
b1 +
0)
b10 "
b10 *
1!
b100 %
b100 &
b100 ,
#6000
b1 +
0)
b10 "
b10 *
1!
b101 %
b101 &
b101 ,
#7000
b1 +
0)
b10 "
b10 *
1!
b110 %
b110 &
b110 ,
#8000
b1 +
0)
b10 "
b10 *
1!
b111 %
b111 &
b111 ,
#9000
b10 +
0)
b11 "
b11 *
1!
b1000 %
b1000 &
b1000 ,
#10000
b10 +
0)
b11 "
b11 *
1!
b1001 %
b1001 &
b1001 ,
#11000
b10 +
0)
b11 "
b11 *
1!
b1010 %
b1010 &
b1010 ,
#12000
b10 +
0)
b11 "
b11 *
1!
b1011 %
b1011 &
b1011 ,
#13000
b10 +
0)
b11 "
b11 *
1!
b1100 %
b1100 &
b1100 ,
#14000
b10 +
0)
b11 "
b11 *
1!
b1101 %
b1101 &
b1101 ,
#15000
b10 +
0)
b11 "
b11 *
1!
b1110 %
b1110 &
b1110 ,
#16000
b10 +
0)
b11 "
b11 *
1!
b1111 %
b1111 &
b1111 ,
#17000
b11 +
0)
b100 "
b100 *
1!
b10000 %
b10000 &
b10000 ,
#18000
b11 +
0)
b100 "
b100 *
1!
b10001 %
b10001 &
b10001 ,
#19000
b11 +
0)
b100 "
b100 *
1!
b10010 %
b10010 &
b10010 ,
#20000
b11 +
0)
b100 "
b100 *
1!
b10011 %
b10011 &
b10011 ,
#21000
b11 +
0)
b100 "
b100 *
1!
b10100 %
b10100 &
b10100 ,
#22000
b11 +
0)
b100 "
b100 *
1!
b10101 %
b10101 &
b10101 ,
#23000
b11 +
0)
b100 "
b100 *
1!
b10110 %
b10110 &
b10110 ,
#24000
b11 +
0)
b100 "
b100 *
1!
b10111 %
b10111 &
b10111 ,
#25000
b11 +
0)
b100 "
b100 *
1!
b11000 %
b11000 &
b11000 ,
#26000
b11 +
0)
b100 "
b100 *
1!
b11001 %
b11001 &
b11001 ,
#27000
b11 +
0)
b100 "
b100 *
1!
b11010 %
b11010 &
b11010 ,
#28000
b11 +
0)
b100 "
b100 *
1!
b11011 %
b11011 &
b11011 ,
#29000
b11 +
0)
b100 "
b100 *
1!
b11100 %
b11100 &
b11100 ,
#30000
b11 +
0)
b100 "
b100 *
1!
b11101 %
b11101 &
b11101 ,
#31000
b11 +
0)
b100 "
b100 *
1!
b11110 %
b11110 &
b11110 ,
#32000
b11 +
0)
b100 "
b100 *
1!
b11111 %
b11111 &
b11111 ,
#33000
b100 +
0)
b101 "
b101 *
1!
b100000 %
b100000 &
b100000 ,
#34000
b100 +
0)
b101 "
b101 *
1!
b100001 %
b100001 &
b100001 ,
#35000
b100 +
0)
b101 "
b101 *
1!
b100010 %
b100010 &
b100010 ,
#36000
b100 +
0)
b101 "
b101 *
1!
b100011 %
b100011 &
b100011 ,
#37000
b100 +
0)
b101 "
b101 *
1!
b100100 %
b100100 &
b100100 ,
#38000
b100 +
0)
b101 "
b101 *
1!
b100101 %
b100101 &
b100101 ,
#39000
b100 +
0)
b101 "
b101 *
1!
b100110 %
b100110 &
b100110 ,
#40000
b100 +
0)
b101 "
b101 *
1!
b100111 %
b100111 &
b100111 ,
#41000
b100 +
0)
b101 "
b101 *
1!
b101000 %
b101000 &
b101000 ,
#42000
b100 +
0)
b101 "
b101 *
1!
b101001 %
b101001 &
b101001 ,
#43000
b100 +
0)
b101 "
b101 *
1!
b101010 %
b101010 &
b101010 ,
#44000
b100 +
0)
b101 "
b101 *
1!
b101011 %
b101011 &
b101011 ,
#45000
b100 +
0)
b101 "
b101 *
1!
b101100 %
b101100 &
b101100 ,
#46000
b100 +
0)
b101 "
b101 *
1!
b101101 %
b101101 &
b101101 ,
#47000
b100 +
0)
b101 "
b101 *
1!
b101110 %
b101110 &
b101110 ,
#48000
b100 +
0)
b101 "
b101 *
1!
b101111 %
b101111 &
b101111 ,
#49000
b100 +
0)
b101 "
b101 *
1!
b110000 %
b110000 &
b110000 ,
#50000
b100 +
0)
b101 "
b101 *
1!
b110001 %
b110001 &
b110001 ,
#51000
b100 +
0)
b101 "
b101 *
1!
b110010 %
b110010 &
b110010 ,
#52000
b100 +
0)
b101 "
b101 *
1!
b110011 %
b110011 &
b110011 ,
#53000
b100 +
0)
b101 "
b101 *
1!
b110100 %
b110100 &
b110100 ,
#54000
b100 +
0)
b101 "
b101 *
1!
b110101 %
b110101 &
b110101 ,
#55000
b100 +
0)
b101 "
b101 *
1!
b110110 %
b110110 &
b110110 ,
#56000
b100 +
0)
b101 "
b101 *
1!
b110111 %
b110111 &
b110111 ,
#57000
b100 +
0)
b101 "
b101 *
1!
b111000 %
b111000 &
b111000 ,
#58000
b100 +
0)
b101 "
b101 *
1!
b111001 %
b111001 &
b111001 ,
#59000
b100 +
0)
b101 "
b101 *
1!
b111010 %
b111010 &
b111010 ,
#60000
b100 +
0)
b101 "
b101 *
1!
b111011 %
b111011 &
b111011 ,
#61000
b100 +
0)
b101 "
b101 *
1!
b111100 %
b111100 &
b111100 ,
#62000
b100 +
0)
b101 "
b101 *
1!
b111101 %
b111101 &
b111101 ,
#63000
b100 +
0)
b101 "
b101 *
1!
b111110 %
b111110 &
b111110 ,
#64000
b100 +
0)
b101 "
b101 *
1!
b111111 %
b111111 &
b111111 ,
#65000
b101 +
0)
b110 "
b110 *
1!
b1000000 %
b1000000 &
b1000000 ,
#66000
b101 +
0)
b110 "
b110 *
1!
b1000001 %
b1000001 &
b1000001 ,
#67000
b101 +
0)
b110 "
b110 *
1!
b1000010 %
b1000010 &
b1000010 ,
#68000
b101 +
0)
b110 "
b110 *
1!
b1000011 %
b1000011 &
b1000011 ,
#69000
b101 +
0)
b110 "
b110 *
1!
b1000100 %
b1000100 &
b1000100 ,
#70000
b101 +
0)
b110 "
b110 *
1!
b1000101 %
b1000101 &
b1000101 ,
#71000
b101 +
0)
b110 "
b110 *
1!
b1000110 %
b1000110 &
b1000110 ,
#72000
b101 +
0)
b110 "
b110 *
1!
b1000111 %
b1000111 &
b1000111 ,
#73000
b101 +
0)
b110 "
b110 *
1!
b1001000 %
b1001000 &
b1001000 ,
#74000
b101 +
0)
b110 "
b110 *
1!
b1001001 %
b1001001 &
b1001001 ,
#75000
b101 +
0)
b110 "
b110 *
1!
b1001010 %
b1001010 &
b1001010 ,
#76000
b101 +
0)
b110 "
b110 *
1!
b1001011 %
b1001011 &
b1001011 ,
#77000
b101 +
0)
b110 "
b110 *
1!
b1001100 %
b1001100 &
b1001100 ,
#78000
b101 +
0)
b110 "
b110 *
1!
b1001101 %
b1001101 &
b1001101 ,
#79000
b101 +
0)
b110 "
b110 *
1!
b1001110 %
b1001110 &
b1001110 ,
#80000
b101 +
0)
b110 "
b110 *
1!
b1001111 %
b1001111 &
b1001111 ,
#81000
b101 +
0)
b110 "
b110 *
1!
b1010000 %
b1010000 &
b1010000 ,
#82000
b101 +
0)
b110 "
b110 *
1!
b1010001 %
b1010001 &
b1010001 ,
#83000
b101 +
0)
b110 "
b110 *
1!
b1010010 %
b1010010 &
b1010010 ,
#84000
b101 +
0)
b110 "
b110 *
1!
b1010011 %
b1010011 &
b1010011 ,
#85000
b101 +
0)
b110 "
b110 *
1!
b1010100 %
b1010100 &
b1010100 ,
#86000
b101 +
0)
b110 "
b110 *
1!
b1010101 %
b1010101 &
b1010101 ,
#87000
b101 +
0)
b110 "
b110 *
1!
b1010110 %
b1010110 &
b1010110 ,
#88000
b101 +
0)
b110 "
b110 *
1!
b1010111 %
b1010111 &
b1010111 ,
#89000
b101 +
0)
b110 "
b110 *
1!
b1011000 %
b1011000 &
b1011000 ,
#90000
b101 +
0)
b110 "
b110 *
1!
b1011001 %
b1011001 &
b1011001 ,
#91000
b101 +
0)
b110 "
b110 *
1!
b1011010 %
b1011010 &
b1011010 ,
#92000
b101 +
0)
b110 "
b110 *
1!
b1011011 %
b1011011 &
b1011011 ,
#93000
b101 +
0)
b110 "
b110 *
1!
b1011100 %
b1011100 &
b1011100 ,
#94000
b101 +
0)
b110 "
b110 *
1!
b1011101 %
b1011101 &
b1011101 ,
#95000
b101 +
0)
b110 "
b110 *
1!
b1011110 %
b1011110 &
b1011110 ,
#96000
b101 +
0)
b110 "
b110 *
1!
b1011111 %
b1011111 &
b1011111 ,
#97000
b101 +
0)
b110 "
b110 *
1!
b1100000 %
b1100000 &
b1100000 ,
#98000
b101 +
0)
b110 "
b110 *
1!
b1100001 %
b1100001 &
b1100001 ,
#99000
b101 +
0)
b110 "
b110 *
1!
b1100010 %
b1100010 &
b1100010 ,
#100000
b101 +
0)
b110 "
b110 *
1!
b1100011 %
b1100011 &
b1100011 ,
#101000
b101 +
0)
b110 "
b110 *
1!
b1100100 %
b1100100 &
b1100100 ,
#102000
b101 +
0)
b110 "
b110 *
1!
b1100101 %
b1100101 &
b1100101 ,
#103000
b101 +
0)
b110 "
b110 *
1!
b1100110 %
b1100110 &
b1100110 ,
#104000
b101 +
0)
b110 "
b110 *
1!
b1100111 %
b1100111 &
b1100111 ,
#105000
b101 +
0)
b110 "
b110 *
1!
b1101000 %
b1101000 &
b1101000 ,
#106000
b101 +
0)
b110 "
b110 *
1!
b1101001 %
b1101001 &
b1101001 ,
#107000
b101 +
0)
b110 "
b110 *
1!
b1101010 %
b1101010 &
b1101010 ,
#108000
b101 +
0)
b110 "
b110 *
1!
b1101011 %
b1101011 &
b1101011 ,
#109000
b101 +
0)
b110 "
b110 *
1!
b1101100 %
b1101100 &
b1101100 ,
#110000
b101 +
0)
b110 "
b110 *
1!
b1101101 %
b1101101 &
b1101101 ,
#111000
b101 +
0)
b110 "
b110 *
1!
b1101110 %
b1101110 &
b1101110 ,
#112000
b101 +
0)
b110 "
b110 *
1!
b1101111 %
b1101111 &
b1101111 ,
#113000
b101 +
0)
b110 "
b110 *
1!
b1110000 %
b1110000 &
b1110000 ,
#114000
b101 +
0)
b110 "
b110 *
1!
b1110001 %
b1110001 &
b1110001 ,
#115000
b101 +
0)
b110 "
b110 *
1!
b1110010 %
b1110010 &
b1110010 ,
#116000
b101 +
0)
b110 "
b110 *
1!
b1110011 %
b1110011 &
b1110011 ,
#117000
b101 +
0)
b110 "
b110 *
1!
b1110100 %
b1110100 &
b1110100 ,
#118000
b101 +
0)
b110 "
b110 *
1!
b1110101 %
b1110101 &
b1110101 ,
#119000
b101 +
0)
b110 "
b110 *
1!
b1110110 %
b1110110 &
b1110110 ,
#120000
b101 +
0)
b110 "
b110 *
1!
b1110111 %
b1110111 &
b1110111 ,
#121000
b101 +
0)
b110 "
b110 *
1!
b1111000 %
b1111000 &
b1111000 ,
#122000
b101 +
0)
b110 "
b110 *
1!
b1111001 %
b1111001 &
b1111001 ,
#123000
b101 +
0)
b110 "
b110 *
1!
b1111010 %
b1111010 &
b1111010 ,
#124000
b101 +
0)
b110 "
b110 *
1!
b1111011 %
b1111011 &
b1111011 ,
#125000
b101 +
0)
b110 "
b110 *
1!
b1111100 %
b1111100 &
b1111100 ,
#126000
b101 +
0)
b110 "
b110 *
1!
b1111101 %
b1111101 &
b1111101 ,
#127000
b101 +
0)
b110 "
b110 *
1!
b1111110 %
b1111110 &
b1111110 ,
#128000
b101 +
0)
b110 "
b110 *
1!
b1111111 %
b1111111 &
b1111111 ,
#129000
b110 +
0)
b111 "
b111 *
1!
b10000000 %
b10000000 &
b10000000 ,
#130000
b110 +
0)
b111 "
b111 *
1!
b10000001 %
b10000001 &
b10000001 ,
#131000
b110 +
0)
b111 "
b111 *
1!
b10000010 %
b10000010 &
b10000010 ,
#132000
b110 +
0)
b111 "
b111 *
1!
b10000011 %
b10000011 &
b10000011 ,
#133000
b110 +
0)
b111 "
b111 *
1!
b10000100 %
b10000100 &
b10000100 ,
#134000
b110 +
0)
b111 "
b111 *
1!
b10000101 %
b10000101 &
b10000101 ,
#135000
b110 +
0)
b111 "
b111 *
1!
b10000110 %
b10000110 &
b10000110 ,
#136000
b110 +
0)
b111 "
b111 *
1!
b10000111 %
b10000111 &
b10000111 ,
#137000
b110 +
0)
b111 "
b111 *
1!
b10001000 %
b10001000 &
b10001000 ,
#138000
b110 +
0)
b111 "
b111 *
1!
b10001001 %
b10001001 &
b10001001 ,
#139000
b110 +
0)
b111 "
b111 *
1!
b10001010 %
b10001010 &
b10001010 ,
#140000
b110 +
0)
b111 "
b111 *
1!
b10001011 %
b10001011 &
b10001011 ,
#141000
b110 +
0)
b111 "
b111 *
1!
b10001100 %
b10001100 &
b10001100 ,
#142000
b110 +
0)
b111 "
b111 *
1!
b10001101 %
b10001101 &
b10001101 ,
#143000
b110 +
0)
b111 "
b111 *
1!
b10001110 %
b10001110 &
b10001110 ,
#144000
b110 +
0)
b111 "
b111 *
1!
b10001111 %
b10001111 &
b10001111 ,
#145000
b110 +
0)
b111 "
b111 *
1!
b10010000 %
b10010000 &
b10010000 ,
#146000
b110 +
0)
b111 "
b111 *
1!
b10010001 %
b10010001 &
b10010001 ,
#147000
b110 +
0)
b111 "
b111 *
1!
b10010010 %
b10010010 &
b10010010 ,
#148000
b110 +
0)
b111 "
b111 *
1!
b10010011 %
b10010011 &
b10010011 ,
#149000
b110 +
0)
b111 "
b111 *
1!
b10010100 %
b10010100 &
b10010100 ,
#150000
b110 +
0)
b111 "
b111 *
1!
b10010101 %
b10010101 &
b10010101 ,
#151000
b110 +
0)
b111 "
b111 *
1!
b10010110 %
b10010110 &
b10010110 ,
#152000
b110 +
0)
b111 "
b111 *
1!
b10010111 %
b10010111 &
b10010111 ,
#153000
b110 +
0)
b111 "
b111 *
1!
b10011000 %
b10011000 &
b10011000 ,
#154000
b110 +
0)
b111 "
b111 *
1!
b10011001 %
b10011001 &
b10011001 ,
#155000
b110 +
0)
b111 "
b111 *
1!
b10011010 %
b10011010 &
b10011010 ,
#156000
b110 +
0)
b111 "
b111 *
1!
b10011011 %
b10011011 &
b10011011 ,
#157000
b110 +
0)
b111 "
b111 *
1!
b10011100 %
b10011100 &
b10011100 ,
#158000
b110 +
0)
b111 "
b111 *
1!
b10011101 %
b10011101 &
b10011101 ,
#159000
b110 +
0)
b111 "
b111 *
1!
b10011110 %
b10011110 &
b10011110 ,
#160000
b110 +
0)
b111 "
b111 *
1!
b10011111 %
b10011111 &
b10011111 ,
#161000
b110 +
0)
b111 "
b111 *
1!
b10100000 %
b10100000 &
b10100000 ,
#162000
b110 +
0)
b111 "
b111 *
1!
b10100001 %
b10100001 &
b10100001 ,
#163000
b110 +
0)
b111 "
b111 *
1!
b10100010 %
b10100010 &
b10100010 ,
#164000
b110 +
0)
b111 "
b111 *
1!
b10100011 %
b10100011 &
b10100011 ,
#165000
b110 +
0)
b111 "
b111 *
1!
b10100100 %
b10100100 &
b10100100 ,
#166000
b110 +
0)
b111 "
b111 *
1!
b10100101 %
b10100101 &
b10100101 ,
#167000
b110 +
0)
b111 "
b111 *
1!
b10100110 %
b10100110 &
b10100110 ,
#168000
b110 +
0)
b111 "
b111 *
1!
b10100111 %
b10100111 &
b10100111 ,
#169000
b110 +
0)
b111 "
b111 *
1!
b10101000 %
b10101000 &
b10101000 ,
#170000
b110 +
0)
b111 "
b111 *
1!
b10101001 %
b10101001 &
b10101001 ,
#171000
b110 +
0)
b111 "
b111 *
1!
b10101010 %
b10101010 &
b10101010 ,
#172000
b110 +
0)
b111 "
b111 *
1!
b10101011 %
b10101011 &
b10101011 ,
#173000
b110 +
0)
b111 "
b111 *
1!
b10101100 %
b10101100 &
b10101100 ,
#174000
b110 +
0)
b111 "
b111 *
1!
b10101101 %
b10101101 &
b10101101 ,
#175000
b110 +
0)
b111 "
b111 *
1!
b10101110 %
b10101110 &
b10101110 ,
#176000
b110 +
0)
b111 "
b111 *
1!
b10101111 %
b10101111 &
b10101111 ,
#177000
b110 +
0)
b111 "
b111 *
1!
b10110000 %
b10110000 &
b10110000 ,
#178000
b110 +
0)
b111 "
b111 *
1!
b10110001 %
b10110001 &
b10110001 ,
#179000
b110 +
0)
b111 "
b111 *
1!
b10110010 %
b10110010 &
b10110010 ,
#180000
b110 +
0)
b111 "
b111 *
1!
b10110011 %
b10110011 &
b10110011 ,
#181000
b110 +
0)
b111 "
b111 *
1!
b10110100 %
b10110100 &
b10110100 ,
#182000
b110 +
0)
b111 "
b111 *
1!
b10110101 %
b10110101 &
b10110101 ,
#183000
b110 +
0)
b111 "
b111 *
1!
b10110110 %
b10110110 &
b10110110 ,
#184000
b110 +
0)
b111 "
b111 *
1!
b10110111 %
b10110111 &
b10110111 ,
#185000
b110 +
0)
b111 "
b111 *
1!
b10111000 %
b10111000 &
b10111000 ,
#186000
b110 +
0)
b111 "
b111 *
1!
b10111001 %
b10111001 &
b10111001 ,
#187000
b110 +
0)
b111 "
b111 *
1!
b10111010 %
b10111010 &
b10111010 ,
#188000
b110 +
0)
b111 "
b111 *
1!
b10111011 %
b10111011 &
b10111011 ,
#189000
b110 +
0)
b111 "
b111 *
1!
b10111100 %
b10111100 &
b10111100 ,
#190000
b110 +
0)
b111 "
b111 *
1!
b10111101 %
b10111101 &
b10111101 ,
#191000
b110 +
0)
b111 "
b111 *
1!
b10111110 %
b10111110 &
b10111110 ,
#192000
b110 +
0)
b111 "
b111 *
1!
b10111111 %
b10111111 &
b10111111 ,
#193000
b110 +
0)
b111 "
b111 *
1!
b11000000 %
b11000000 &
b11000000 ,
#194000
b110 +
0)
b111 "
b111 *
1!
b11000001 %
b11000001 &
b11000001 ,
#195000
b110 +
0)
b111 "
b111 *
1!
b11000010 %
b11000010 &
b11000010 ,
#196000
b110 +
0)
b111 "
b111 *
1!
b11000011 %
b11000011 &
b11000011 ,
#197000
b110 +
0)
b111 "
b111 *
1!
b11000100 %
b11000100 &
b11000100 ,
#198000
b110 +
0)
b111 "
b111 *
1!
b11000101 %
b11000101 &
b11000101 ,
#199000
b110 +
0)
b111 "
b111 *
1!
b11000110 %
b11000110 &
b11000110 ,
#200000
b110 +
0)
b111 "
b111 *
1!
b11000111 %
b11000111 &
b11000111 ,
#201000
b110 +
0)
b111 "
b111 *
1!
b11001000 %
b11001000 &
b11001000 ,
#202000
b110 +
0)
b111 "
b111 *
1!
b11001001 %
b11001001 &
b11001001 ,
#203000
b110 +
0)
b111 "
b111 *
1!
b11001010 %
b11001010 &
b11001010 ,
#204000
b110 +
0)
b111 "
b111 *
1!
b11001011 %
b11001011 &
b11001011 ,
#205000
b110 +
0)
b111 "
b111 *
1!
b11001100 %
b11001100 &
b11001100 ,
#206000
b110 +
0)
b111 "
b111 *
1!
b11001101 %
b11001101 &
b11001101 ,
#207000
b110 +
0)
b111 "
b111 *
1!
b11001110 %
b11001110 &
b11001110 ,
#208000
b110 +
0)
b111 "
b111 *
1!
b11001111 %
b11001111 &
b11001111 ,
#209000
b110 +
0)
b111 "
b111 *
1!
b11010000 %
b11010000 &
b11010000 ,
#210000
b110 +
0)
b111 "
b111 *
1!
b11010001 %
b11010001 &
b11010001 ,
#211000
b110 +
0)
b111 "
b111 *
1!
b11010010 %
b11010010 &
b11010010 ,
#212000
b110 +
0)
b111 "
b111 *
1!
b11010011 %
b11010011 &
b11010011 ,
#213000
b110 +
0)
b111 "
b111 *
1!
b11010100 %
b11010100 &
b11010100 ,
#214000
b110 +
0)
b111 "
b111 *
1!
b11010101 %
b11010101 &
b11010101 ,
#215000
b110 +
0)
b111 "
b111 *
1!
b11010110 %
b11010110 &
b11010110 ,
#216000
b110 +
0)
b111 "
b111 *
1!
b11010111 %
b11010111 &
b11010111 ,
#217000
b110 +
0)
b111 "
b111 *
1!
b11011000 %
b11011000 &
b11011000 ,
#218000
b110 +
0)
b111 "
b111 *
1!
b11011001 %
b11011001 &
b11011001 ,
#219000
b110 +
0)
b111 "
b111 *
1!
b11011010 %
b11011010 &
b11011010 ,
#220000
b110 +
0)
b111 "
b111 *
1!
b11011011 %
b11011011 &
b11011011 ,
#221000
b110 +
0)
b111 "
b111 *
1!
b11011100 %
b11011100 &
b11011100 ,
#222000
b110 +
0)
b111 "
b111 *
1!
b11011101 %
b11011101 &
b11011101 ,
#223000
b110 +
0)
b111 "
b111 *
1!
b11011110 %
b11011110 &
b11011110 ,
#224000
b110 +
0)
b111 "
b111 *
1!
b11011111 %
b11011111 &
b11011111 ,
#225000
b110 +
0)
b111 "
b111 *
1!
b11100000 %
b11100000 &
b11100000 ,
#226000
b110 +
0)
b111 "
b111 *
1!
b11100001 %
b11100001 &
b11100001 ,
#227000
b110 +
0)
b111 "
b111 *
1!
b11100010 %
b11100010 &
b11100010 ,
#228000
b110 +
0)
b111 "
b111 *
1!
b11100011 %
b11100011 &
b11100011 ,
#229000
b110 +
0)
b111 "
b111 *
1!
b11100100 %
b11100100 &
b11100100 ,
#230000
b110 +
0)
b111 "
b111 *
1!
b11100101 %
b11100101 &
b11100101 ,
#231000
b110 +
0)
b111 "
b111 *
1!
b11100110 %
b11100110 &
b11100110 ,
#232000
b110 +
0)
b111 "
b111 *
1!
b11100111 %
b11100111 &
b11100111 ,
#233000
b110 +
0)
b111 "
b111 *
1!
b11101000 %
b11101000 &
b11101000 ,
#234000
b110 +
0)
b111 "
b111 *
1!
b11101001 %
b11101001 &
b11101001 ,
#235000
b110 +
0)
b111 "
b111 *
1!
b11101010 %
b11101010 &
b11101010 ,
#236000
b110 +
0)
b111 "
b111 *
1!
b11101011 %
b11101011 &
b11101011 ,
#237000
b110 +
0)
b111 "
b111 *
1!
b11101100 %
b11101100 &
b11101100 ,
#238000
b110 +
0)
b111 "
b111 *
1!
b11101101 %
b11101101 &
b11101101 ,
#239000
b110 +
0)
b111 "
b111 *
1!
b11101110 %
b11101110 &
b11101110 ,
#240000
b110 +
0)
b111 "
b111 *
1!
b11101111 %
b11101111 &
b11101111 ,
#241000
b110 +
0)
b111 "
b111 *
1!
b11110000 %
b11110000 &
b11110000 ,
#242000
b110 +
0)
b111 "
b111 *
1!
b11110001 %
b11110001 &
b11110001 ,
#243000
b110 +
0)
b111 "
b111 *
1!
b11110010 %
b11110010 &
b11110010 ,
#244000
b110 +
0)
b111 "
b111 *
1!
b11110011 %
b11110011 &
b11110011 ,
#245000
b110 +
0)
b111 "
b111 *
1!
b11110100 %
b11110100 &
b11110100 ,
#246000
b110 +
0)
b111 "
b111 *
1!
b11110101 %
b11110101 &
b11110101 ,
#247000
b110 +
0)
b111 "
b111 *
1!
b11110110 %
b11110110 &
b11110110 ,
#248000
b110 +
0)
b111 "
b111 *
1!
b11110111 %
b11110111 &
b11110111 ,
#249000
b110 +
0)
b111 "
b111 *
1!
b11111000 %
b11111000 &
b11111000 ,
#250000
b110 +
0)
b111 "
b111 *
1!
b11111001 %
b11111001 &
b11111001 ,
#251000
b110 +
0)
b111 "
b111 *
1!
b11111010 %
b11111010 &
b11111010 ,
#252000
b110 +
0)
b111 "
b111 *
1!
b11111011 %
b11111011 &
b11111011 ,
#253000
b110 +
0)
b111 "
b111 *
1!
b11111100 %
b11111100 &
b11111100 ,
#254000
b110 +
0)
b111 "
b111 *
1!
b11111101 %
b11111101 &
b11111101 ,
#255000
b110 +
0)
b111 "
b111 *
1!
b11111110 %
b11111110 &
b11111110 ,
#256000
b110 +
0)
b111 "
b111 *
1!
b11111111 %
b11111111 &
b11111111 ,
#257000
b100000000 ,
